icestick/scratch1/design.v
// T Flip Flop - toggles the output whenever the input is high
module tff(input d, rst, clk, output LED5);
  reg q;
  wire Q; 
  wire clk_out;

  clk_div u1 (clk, clk_out);
  defparam u1.DIVISOR = 25'd2;

  // toggle flip-flop
  always @(posedge clk_out or posedge rst) begin
    if (rst)
      q <= 1'b0;
    else 
      if (d) 
        q <= ~q;
      else 
        q <= q;
  end

  dff u2 (clk_out, q, Q); // extra debounce filtering
  assign LED5 = Q;
endmodule

module dff (input clk, d, output reg q);
  always @(posedge clk)
    q <= d;
endmodule

// 12 Mhz master clock
module clk_div ( 
    input clk, 
    output reg clk_out
  );

  reg [24:0] counter = 25'd0;
  parameter DIVISOR = 25'd12000000; // master clk(12Mhz) divided by divisor(12Mhz) generates a 1Hz signal

  always @(posedge clk) begin
    counter <= counter + 1;
    if (counter >= (DIVISOR-1))
      counter <= 25'd0;
    clk_out <= (counter < DIVISOR/2) ? 1'b1 : 1'b0; // half on half off
  end
endmodule

icestick/scratch1/design_tb.v
`include "design.v"
`timescale 1ns/1ps
module tff_tb;
  reg d, rst, clk;
  wire q;

  tff UUT (.d(d), .rst(rst), .clk(clk), .LED5(q));
  initial begin
    clk <= 1'b0;
    rst <= 1'b1;
  end 
  initial begin 
    $dumpvars;
    #5; rst <= 1'b0;
    d <= 1'b1; #17; // adjust this value to get d to drop low when q is low/high to keep q's state
    d <= 1'b0;
    #500;
    $finish;
  end
  always begin
    #1 clk <= ~clk;
  end
endmodule

icestick/scratch1/dump.vcd
$date
	Sun Jun 26 17:32:58 2022
$end
$version
	Icarus Verilog
$end
$timescale
	1ps
$end
$scope module tff_tb $end
$var wire 1 ! q $end
$var reg 1 " clk $end
$var reg 1 # d $end
$var reg 1 $ rst $end
$scope module UUT $end
$var wire 1 ! LED5 $end
$var wire 1 " clk $end
$var wire 1 # d $end
$var wire 1 $ rst $end
$var wire 1 % clk_out $end
$var wire 1 & Q $end
$var reg 1 ' q $end
$scope module u1 $end
$var wire 1 " clk $end
$var reg 1 % clk_out $end
$var reg 25 ( counter [24:0] $end
$upscope $end
$scope module u2 $end
$var wire 1 % clk $end
$var wire 1 ' d $end
$var reg 1 & q $end
$upscope $end
$upscope $end
$upscope $end
$enddefinitions $end
#0
$dumpvars
b0 (
0'
x&
x%
1$
x#
0"
x!
$end
#1000
0!
0&
1%
b1 (
1"
#2000
0"
#3000
0%
b0 (
1"
#4000
0"
#5000
1'
1%
b1 (
1"
1#
0$
#6000
0"
#7000
0%
b0 (
1"
#8000
0"
#9000
1!
1&
0'
1%
b1 (
1"
#10000
0"
#11000
0%
b0 (
1"
#12000
0"
#13000
0!
0&
1'
1%
b1 (
1"
#14000
0"
#15000
0%
b0 (
1"
#16000
0"
#17000
1!
1&
0'
1%
b1 (
1"
#18000
0"
#19000
0%
b0 (
1"
#20000
0"
#21000
0!
0&
1'
1%
b1 (
1"
#22000
0"
0#
#23000
0%
b0 (
1"
#24000
0"
#25000
1!
1&
1%
b1 (
1"
#26000
0"
#27000
0%
b0 (
1"
#28000
0"
#29000
1%
b1 (
1"
#30000
0"
#31000
0%
b0 (
1"
#32000
0"
#33000
1%
b1 (
1"
#34000
0"
#35000
0%
b0 (
1"
#36000
0"
#37000
1%
b1 (
1"
#38000
0"
#39000
0%
b0 (
1"
#40000
0"
#41000
1%
b1 (
1"
#42000
0"
#43000
0%
b0 (
1"
#44000
0"
#45000
1%
b1 (
1"
#46000
0"
#47000
0%
b0 (
1"
#48000
0"
#49000
1%
b1 (
1"
#50000
0"
#51000
0%
b0 (
1"
#52000
0"
#53000
1%
b1 (
1"
#54000
0"
#55000
0%
b0 (
1"
#56000
0"
#57000
1%
b1 (
1"
#58000
0"
#59000
0%
b0 (
1"
#60000
0"
#61000
1%
b1 (
1"
#62000
0"
#63000
0%
b0 (
1"
#64000
0"
#65000
1%
b1 (
1"
#66000
0"
#67000
0%
b0 (
1"
#68000
0"
#69000
1%
b1 (
1"
#70000
0"
#71000
0%
b0 (
1"
#72000
0"
#73000
1%
b1 (
1"
#74000
0"
#75000
0%
b0 (
1"
#76000
0"
#77000
1%
b1 (
1"
#78000
0"
#79000
0%
b0 (
1"
#80000
0"
#81000
1%
b1 (
1"
#82000
0"
#83000
0%
b0 (
1"
#84000
0"
#85000
1%
b1 (
1"
#86000
0"
#87000
0%
b0 (
1"
#88000
0"
#89000
1%
b1 (
1"
#90000
0"
#91000
0%
b0 (
1"
#92000
0"
#93000
1%
b1 (
1"
#94000
0"
#95000
0%
b0 (
1"
#96000
0"
#97000
1%
b1 (
1"
#98000
0"
#99000
0%
b0 (
1"
#100000
0"
#101000
1%
b1 (
1"
#102000
0"
#103000
0%
b0 (
1"
#104000
0"
#105000
1%
b1 (
1"
#106000
0"
#107000
0%
b0 (
1"
#108000
0"
#109000
1%
b1 (
1"
#110000
0"
#111000
0%
b0 (
1"
#112000
0"
#113000
1%
b1 (
1"
#114000
0"
#115000
0%
b0 (
1"
#116000
0"
#117000
1%
b1 (
1"
#118000
0"
#119000
0%
b0 (
1"
#120000
0"
#121000
1%
b1 (
1"
#122000
0"
#123000
0%
b0 (
1"
#124000
0"
#125000
1%
b1 (
1"
#126000
0"
#127000
0%
b0 (
1"
#128000
0"
#129000
1%
b1 (
1"
#130000
0"
#131000
0%
b0 (
1"
#132000
0"
#133000
1%
b1 (
1"
#134000
0"
#135000
0%
b0 (
1"
#136000
0"
#137000
1%
b1 (
1"
#138000
0"
#139000
0%
b0 (
1"
#140000
0"
#141000
1%
b1 (
1"
#142000
0"
#143000
0%
b0 (
1"
#144000
0"
#145000
1%
b1 (
1"
#146000
0"
#147000
0%
b0 (
1"
#148000
0"
#149000
1%
b1 (
1"
#150000
0"
#151000
0%
b0 (
1"
#152000
0"
#153000
1%
b1 (
1"
#154000
0"
#155000
0%
b0 (
1"
#156000
0"
#157000
1%
b1 (
1"
#158000
0"
#159000
0%
b0 (
1"
#160000
0"
#161000
1%
b1 (
1"
#162000
0"
#163000
0%
b0 (
1"
#164000
0"
#165000
1%
b1 (
1"
#166000
0"
#167000
0%
b0 (
1"
#168000
0"
#169000
1%
b1 (
1"
#170000
0"
#171000
0%
b0 (
1"
#172000
0"
#173000
1%
b1 (
1"
#174000
0"
#175000
0%
b0 (
1"
#176000
0"
#177000
1%
b1 (
1"
#178000
0"
#179000
0%
b0 (
1"
#180000
0"
#181000
1%
b1 (
1"
#182000
0"
#183000
0%
b0 (
1"
#184000
0"
#185000
1%
b1 (
1"
#186000
0"
#187000
0%
b0 (
1"
#188000
0"
#189000
1%
b1 (
1"
#190000
0"
#191000
0%
b0 (
1"
#192000
0"
#193000
1%
b1 (
1"
#194000
0"
#195000
0%
b0 (
1"
#196000
0"
#197000
1%
b1 (
1"
#198000
0"
#199000
0%
b0 (
1"
#200000
0"
#201000
1%
b1 (
1"
#202000
0"
#203000
0%
b0 (
1"
#204000
0"
#205000
1%
b1 (
1"
#206000
0"
#207000
0%
b0 (
1"
#208000
0"
#209000
1%
b1 (
1"
#210000
0"
#211000
0%
b0 (
1"
#212000
0"
#213000
1%
b1 (
1"
#214000
0"
#215000
0%
b0 (
1"
#216000
0"
#217000
1%
b1 (
1"
#218000
0"
#219000
0%
b0 (
1"
#220000
0"
#221000
1%
b1 (
1"
#222000
0"
#223000
0%
b0 (
1"
#224000
0"
#225000
1%
b1 (
1"
#226000
0"
#227000
0%
b0 (
1"
#228000
0"
#229000
1%
b1 (
1"
#230000
0"
#231000
0%
b0 (
1"
#232000
0"
#233000
1%
b1 (
1"
#234000
0"
#235000
0%
b0 (
1"
#236000
0"
#237000
1%
b1 (
1"
#238000
0"
#239000
0%
b0 (
1"
#240000
0"
#241000
1%
b1 (
1"
#242000
0"
#243000
0%
b0 (
1"
#244000
0"
#245000
1%
b1 (
1"
#246000
0"
#247000
0%
b0 (
1"
#248000
0"
#249000
1%
b1 (
1"
#250000
0"
#251000
0%
b0 (
1"
#252000
0"
#253000
1%
b1 (
1"
#254000
0"
#255000
0%
b0 (
1"
#256000
0"
#257000
1%
b1 (
1"
#258000
0"
#259000
0%
b0 (
1"
#260000
0"
#261000
1%
b1 (
1"
#262000
0"
#263000
0%
b0 (
1"
#264000
0"
#265000
1%
b1 (
1"
#266000
0"
#267000
0%
b0 (
1"
#268000
0"
#269000
1%
b1 (
1"
#270000
0"
#271000
0%
b0 (
1"
#272000
0"
#273000
1%
b1 (
1"
#274000
0"
#275000
0%
b0 (
1"
#276000
0"
#277000
1%
b1 (
1"
#278000
0"
#279000
0%
b0 (
1"
#280000
0"
#281000
1%
b1 (
1"
#282000
0"
#283000
0%
b0 (
1"
#284000
0"
#285000
1%
b1 (
1"
#286000
0"
#287000
0%
b0 (
1"
#288000
0"
#289000
1%
b1 (
1"
#290000
0"
#291000
0%
b0 (
1"
#292000
0"
#293000
1%
b1 (
1"
#294000
0"
#295000
0%
b0 (
1"
#296000
0"
#297000
1%
b1 (
1"
#298000
0"
#299000
0%
b0 (
1"
#300000
0"
#301000
1%
b1 (
1"
#302000
0"
#303000
0%
b0 (
1"
#304000
0"
#305000
1%
b1 (
1"
#306000
0"
#307000
0%
b0 (
1"
#308000
0"
#309000
1%
b1 (
1"
#310000
0"
#311000
0%
b0 (
1"
#312000
0"
#313000
1%
b1 (
1"
#314000
0"
#315000
0%
b0 (
1"
#316000
0"
#317000
1%
b1 (
1"
#318000
0"
#319000
0%
b0 (
1"
#320000
0"
#321000
1%
b1 (
1"
#322000
0"
#323000
0%
b0 (
1"
#324000
0"
#325000
1%
b1 (
1"
#326000
0"
#327000
0%
b0 (
1"
#328000
0"
#329000
1%
b1 (
1"
#330000
0"
#331000
0%
b0 (
1"
#332000
0"
#333000
1%
b1 (
1"
#334000
0"
#335000
0%
b0 (
1"
#336000
0"
#337000
1%
b1 (
1"
#338000
0"
#339000
0%
b0 (
1"
#340000
0"
#341000
1%
b1 (
1"
#342000
0"
#343000
0%
b0 (
1"
#344000
0"
#345000
1%
b1 (
1"
#346000
0"
#347000
0%
b0 (
1"
#348000
0"
#349000
1%
b1 (
1"
#350000
0"
#351000
0%
b0 (
1"
#352000
0"
#353000
1%
b1 (
1"
#354000
0"
#355000
0%
b0 (
1"
#356000
0"
#357000
1%
b1 (
1"
#358000
0"
#359000
0%
b0 (
1"
#360000
0"
#361000
1%
b1 (
1"
#362000
0"
#363000
0%
b0 (
1"
#364000
0"
#365000
1%
b1 (
1"
#366000
0"
#367000
0%
b0 (
1"
#368000
0"
#369000
1%
b1 (
1"
#370000
0"
#371000
0%
b0 (
1"
#372000
0"
#373000
1%
b1 (
1"
#374000
0"
#375000
0%
b0 (
1"
#376000
0"
#377000
1%
b1 (
1"
#378000
0"
#379000
0%
b0 (
1"
#380000
0"
#381000
1%
b1 (
1"
#382000
0"
#383000
0%
b0 (
1"
#384000
0"
#385000
1%
b1 (
1"
#386000
0"
#387000
0%
b0 (
1"
#388000
0"
#389000
1%
b1 (
1"
#390000
0"
#391000
0%
b0 (
1"
#392000
0"
#393000
1%
b1 (
1"
#394000
0"
#395000
0%
b0 (
1"
#396000
0"
#397000
1%
b1 (
1"
#398000
0"
#399000
0%
b0 (
1"
#400000
0"
#401000
1%
b1 (
1"
#402000
0"
#403000
0%
b0 (
1"
#404000
0"
#405000
1%
b1 (
1"
#406000
0"
#407000
0%
b0 (
1"
#408000
0"
#409000
1%
b1 (
1"
#410000
0"
#411000
0%
b0 (
1"
#412000
0"
#413000
1%
b1 (
1"
#414000
0"
#415000
0%
b0 (
1"
#416000
0"
#417000
1%
b1 (
1"
#418000
0"
#419000
0%
b0 (
1"
#420000
0"
#421000
1%
b1 (
1"
#422000
0"
#423000
0%
b0 (
1"
#424000
0"
#425000
1%
b1 (
1"
#426000
0"
#427000
0%
b0 (
1"
#428000
0"
#429000
1%
b1 (
1"
#430000
0"
#431000
0%
b0 (
1"
#432000
0"
#433000
1%
b1 (
1"
#434000
0"
#435000
0%
b0 (
1"
#436000
0"
#437000
1%
b1 (
1"
#438000
0"
#439000
0%
b0 (
1"
#440000
0"
#441000
1%
b1 (
1"
#442000
0"
#443000
0%
b0 (
1"
#444000
0"
#445000
1%
b1 (
1"
#446000
0"
#447000
0%
b0 (
1"
#448000
0"
#449000
1%
b1 (
1"
#450000
0"
#451000
0%
b0 (
1"
#452000
0"
#453000
1%
b1 (
1"
#454000
0"
#455000
0%
b0 (
1"
#456000
0"
#457000
1%
b1 (
1"
#458000
0"
#459000
0%
b0 (
1"
#460000
0"
#461000
1%
b1 (
1"
#462000
0"
#463000
0%
b0 (
1"
#464000
0"
#465000
1%
b1 (
1"
#466000
0"
#467000
0%
b0 (
1"
#468000
0"
#469000
1%
b1 (
1"
#470000
0"
#471000
0%
b0 (
1"
#472000
0"
#473000
1%
b1 (
1"
#474000
0"
#475000
0%
b0 (
1"
#476000
0"
#477000
1%
b1 (
1"
#478000
0"
#479000
0%
b0 (
1"
#480000
0"
#481000
1%
b1 (
1"
#482000
0"
#483000
0%
b0 (
1"
#484000
0"
#485000
1%
b1 (
1"
#486000
0"
#487000
0%
b0 (
1"
#488000
0"
#489000
1%
b1 (
1"
#490000
0"
#491000
0%
b0 (
1"
#492000
0"
#493000
1%
b1 (
1"
#494000
0"
#495000
0%
b0 (
1"
#496000
0"
#497000
1%
b1 (
1"
#498000
0"
#499000
0%
b0 (
1"
#500000
0"
#501000
1%
b1 (
1"
#502000
0"
#503000
0%
b0 (
1"
#504000
0"
#505000
1%
b1 (
1"
#506000
0"
#507000
0%
b0 (
1"
#508000
0"
#509000
1%
b1 (
1"
#510000
0"
#511000
0%
b0 (
1"
#512000
0"
#513000
1%
b1 (
1"
#514000
0"
#515000
0%
b0 (
1"
#516000
0"
#517000
1%
b1 (
1"
#518000
0"
#519000
0%
b0 (
1"
#520000
0"
#521000
1%
b1 (
1"
