icestick/scratch0/design.v
`default_nettype none
module top(input clk, output LED5, LED4, LED3);
  reg [15:0] cnt1 = 0;
  reg [6:0] cnt2 = 0;
  reg half_sec_indicator = 0;
  reg [2:0] o_output = 0;

  // Toggling LED to about half a second, but need to divide the clock down from 12 Mhz to be able to do so
  // The 12MHz clock is too fast
  // The first counter will / 2^16 (about 5.46ms)
  // Then the second counter goes to 91 which is 0.497s
  // close enough to 1/2 second 
  always @(posedge clk) begin
    cnt1 <= cnt1 + 16'h8000;
    if (cnt1 == 0)
      if (cnt2 == 2) // sim value 2;
        begin
          cnt2 <= 0;
          half_sec_indicator <= 1; 
        end
      else
        cnt2 <= cnt2 + 1;
    else 
      half_sec_indicator <= 0; 
    
    if (half_sec_indicator == 1)
      o_output <= o_output + 1;
  end  

  assign LED5 = o_output[0];  // 001
  assign LED4 = o_output[1];  // 010
  assign LED3 = o_output[2];  // 100
endmodule

icestick/scratch0/design_tb.v
`include "design.v"
//`timescale 1us/1ns
module top_tb;
  reg clk;
  wire led5, led4, led3;

  top UUT (.clk(clk), .LED5(led5), .LED4(led4), .LED3(led3));

  // clock generator
  initial 
    clk <= 1'b0;
  always begin
    #1 clk <= ~clk;
  end

  initial begin
    $dumpvars;
    $display("led5   led4   led3");
    $monitor(" %b      %b       %b", led5, led4, led3);
    #100;
    $finish;
  end

endmodule

icestick/scratch0/dump.vcd
$date
	Sun Jun 26 13:09:27 2022
$end
$version
	Icarus Verilog
$end
$timescale
	1s
$end
$scope module top_tb $end
$var wire 1 ! led5 $end
$var wire 1 " led4 $end
$var wire 1 # led3 $end
$var reg 1 $ clk $end
$scope module UUT $end
$var wire 1 $ clk $end
$var wire 1 ! LED5 $end
$var wire 1 " LED4 $end
$var wire 1 # LED3 $end
$var reg 16 % cnt1 [15:0] $end
$var reg 7 & cnt2 [6:0] $end
$var reg 1 ' half_sec_indicator $end
$var reg 3 ( o_output [2:0] $end
$upscope $end
$upscope $end
$enddefinitions $end
#0
$dumpvars
b0 (
0'
b0 &
b0 %
0$
0#
0"
0!
$end
#1
b1 &
b1000000000000000 %
1$
#2
0$
#3
b0 %
1$
#4
0$
#5
b10 &
b1000000000000000 %
1$
#6
0$
#7
b0 %
1$
#8
0$
#9
1'
b0 &
b1000000000000000 %
1$
#10
0$
#11
1!
b1 (
0'
b0 %
1$
#12
0$
#13
b1 &
b1000000000000000 %
1$
#14
0$
#15
b0 %
1$
#16
0$
#17
b10 &
b1000000000000000 %
1$
#18
0$
#19
b0 %
1$
#20
0$
#21
1'
b0 &
b1000000000000000 %
1$
#22
0$
#23
0!
1"
b10 (
0'
b0 %
1$
#24
0$
#25
b1 &
b1000000000000000 %
1$
#26
0$
#27
b0 %
1$
#28
0$
#29
b10 &
b1000000000000000 %
1$
#30
0$
#31
b0 %
1$
#32
0$
#33
1'
b0 &
b1000000000000000 %
1$
#34
0$
#35
1!
b11 (
0'
b0 %
1$
#36
0$
#37
b1 &
b1000000000000000 %
1$
#38
0$
#39
b0 %
1$
#40
0$
#41
b10 &
b1000000000000000 %
1$
#42
0$
#43
b0 %
1$
#44
0$
#45
1'
b0 &
b1000000000000000 %
1$
#46
0$
#47
0!
0"
1#
b100 (
0'
b0 %
1$
#48
0$
#49
b1 &
b1000000000000000 %
1$
#50
0$
#51
b0 %
1$
#52
0$
#53
b10 &
b1000000000000000 %
1$
#54
0$
#55
b0 %
1$
#56
0$
#57
1'
b0 &
b1000000000000000 %
1$
#58
0$
#59
1!
b101 (
0'
b0 %
1$
#60
0$
#61
b1 &
b1000000000000000 %
1$
#62
0$
#63
b0 %
1$
#64
0$
#65
b10 &
b1000000000000000 %
1$
#66
0$
#67
b0 %
1$
#68
0$
#69
1'
b0 &
b1000000000000000 %
1$
#70
0$
#71
0!
1"
b110 (
0'
b0 %
1$
#72
0$
#73
b1 &
b1000000000000000 %
1$
#74
0$
#75
b0 %
1$
#76
0$
#77
b10 &
b1000000000000000 %
1$
#78
0$
#79
b0 %
1$
#80
0$
#81
1'
b0 &
b1000000000000000 %
1$
#82
0$
#83
1!
b111 (
0'
b0 %
1$
#84
0$
#85
b1 &
b1000000000000000 %
1$
#86
0$
#87
b0 %
1$
#88
0$
#89
b10 &
b1000000000000000 %
1$
#90
0$
#91
b0 %
1$
#92
0$
#93
1'
b0 &
b1000000000000000 %
1$
#94
0$
#95
0!
0"
0#
b0 (
0'
b0 %
1$
#96
0$
#97
b1 &
b1000000000000000 %
1$
#98
0$
#99
b0 %
1$
