icestick/scratch2/design.v
// Instiantiating a clock divider to drive leds at 1Hz
module top(input clk, output LED5, LED4, LED2);
  wire clk_out;
  clk_div u1 (clk, clk_out);
  //defparam u1.DIVISOR = 25'd2;

  assign LED5 = clk_out;
  assign LED4 = clk_out;
  assign LED2 = clk_out;
endmodule

// 12 Mhz master clock
module clk_div ( 
    input clk, 
    output reg clk_out
  );

  reg [24:0] counter = 25'd0;
  parameter DIVISOR = 25'd12000000; // master clk(12Mhz) divided by divisor(12Mhz) generates a 1Hz signal

  always @(posedge clk) begin
    counter <= counter + 1;
    if (counter >= (DIVISOR-1))
      counter <= 25'd0;
    clk_out <= (counter < DIVISOR/2) ? 1'b1 : 1'b0; // half on half off
  end
endmodule

icestick/scratch2/design_tb.v
`include "design.v"
//`timescale 1ns/1ps

module top_tb;
  reg clk;
  wire led5, led4, led2;
  
  top UUT ( .clk(clk), 
            .LED5(led5), 
            .LED4(led4), 
            .LED2(led2));
  initial
    clk <= 1'b0;
  always begin
    #1 clk <= ~clk;
  end
  initial begin 
    $dumpvars;
    $display("led5 led4 led2");
    $monitor(" %b   %b   %b", led5, led4, led2);
    #100;
    $finish;
  end
endmodule

icestick/scratch2/dump.vcd
$date
	Sun Jun 26 15:20:06 2022
$end
$version
	Icarus Verilog
$end
$timescale
	1s
$end
$scope module top_tb $end
$var wire 1 ! led5 $end
$var wire 1 " led4 $end
$var wire 1 # led2 $end
$var reg 1 $ clk $end
$scope module UUT $end
$var wire 1 # LED2 $end
$var wire 1 " LED4 $end
$var wire 1 ! LED5 $end
$var wire 1 $ clk $end
$var wire 1 % clk_out $end
$scope module u1 $end
$var wire 1 $ clk $end
$var reg 1 % clk_out $end
$var reg 25 & counter [24:0] $end
$upscope $end
$upscope $end
$upscope $end
$enddefinitions $end
#0
$dumpvars
b0 &
x%
0$
x#
x"
x!
$end
#1
1#
1"
1!
1%
b1 &
1$
#2
0$
#3
0#
0"
0!
0%
b0 &
1$
#4
0$
#5
1#
1"
1!
1%
b1 &
1$
#6
0$
#7
0#
0"
0!
0%
b0 &
1$
#8
0$
#9
1#
1"
1!
1%
b1 &
1$
#10
0$
#11
0#
0"
0!
0%
b0 &
1$
#12
0$
#13
1#
1"
1!
1%
b1 &
1$
#14
0$
#15
0#
0"
0!
0%
b0 &
1$
#16
0$
#17
1#
1"
1!
1%
b1 &
1$
#18
0$
#19
0#
0"
0!
0%
b0 &
1$
#20
0$
#21
1#
1"
1!
1%
b1 &
1$
#22
0$
#23
0#
0"
0!
0%
b0 &
1$
#24
0$
#25
1#
1"
1!
1%
b1 &
1$
#26
0$
#27
0#
0"
0!
0%
b0 &
1$
#28
0$
#29
1#
1"
1!
1%
b1 &
1$
#30
0$
#31
0#
0"
0!
0%
b0 &
1$
#32
0$
#33
1#
1"
1!
1%
b1 &
1$
#34
0$
#35
0#
0"
0!
0%
b0 &
1$
#36
0$
#37
1#
1"
1!
1%
b1 &
1$
#38
0$
#39
0#
0"
0!
0%
b0 &
1$
#40
0$
#41
1#
1"
1!
1%
b1 &
1$
#42
0$
#43
0#
0"
0!
0%
b0 &
1$
#44
0$
#45
1#
1"
1!
1%
b1 &
1$
#46
0$
#47
0#
0"
0!
0%
b0 &
1$
#48
0$
#49
1#
1"
1!
1%
b1 &
1$
#50
0$
#51
0#
0"
0!
0%
b0 &
1$
#52
0$
#53
1#
1"
1!
1%
b1 &
1$
#54
0$
#55
0#
0"
0!
0%
b0 &
1$
#56
0$
#57
1#
1"
1!
1%
b1 &
1$
#58
0$
#59
0#
0"
0!
0%
b0 &
1$
#60
0$
#61
1#
1"
1!
1%
b1 &
1$
#62
0$
#63
0#
0"
0!
0%
b0 &
1$
#64
0$
#65
1#
1"
1!
1%
b1 &
1$
#66
0$
#67
0#
0"
0!
0%
b0 &
1$
#68
0$
#69
1#
1"
1!
1%
b1 &
1$
#70
0$
#71
0#
0"
0!
0%
b0 &
1$
#72
0$
#73
1#
1"
1!
1%
b1 &
1$
#74
0$
#75
0#
0"
0!
0%
b0 &
1$
#76
0$
#77
1#
1"
1!
1%
b1 &
1$
#78
0$
#79
0#
0"
0!
0%
b0 &
1$
#80
0$
#81
1#
1"
1!
1%
b1 &
1$
#82
0$
#83
0#
0"
0!
0%
b0 &
1$
#84
0$
#85
1#
1"
1!
1%
b1 &
1$
#86
0$
#87
0#
0"
0!
0%
b0 &
1$
#88
0$
#89
1#
1"
1!
1%
b1 &
1$
#90
0$
#91
0#
0"
0!
0%
b0 &
1$
#92
0$
#93
1#
1"
1!
1%
b1 &
1$
#94
0$
#95
0#
0"
0!
0%
b0 &
1$
#96
0$
#97
1#
1"
1!
1%
b1 &
1$
#98
0$
#99
0#
0"
0!
0%
b0 &
1$
