gates/mux/mux.v
module mux(input a, b, sel, output reg out);
  // sel 1, out = a
  // sel 0, out = b
  always @(a or b or sel)
    if (sel)
      out <= a;
    else 
      out <= b;
endmodule

gates/mux/mux_tb.v
`include "mux.v"

module mux_tb;
  reg a, b, sel;
  wire out;

  mux UUT (a, b, sel, out);
  initial begin
    $dumpvars;
    $display("a  b  sel  out");
    $monitor("%b  %b   %b    %b", a, b, sel, out);
   
    a = 0; b = 0; sel = 0; #5; 
    a = 0; b = 0; sel = 1; #5; 
    a = 0; b = 1; sel = 0; #5; 
    a = 0; b = 1; sel = 1; #5; 
    a = 1; b = 0; sel = 0; #5; 
    a = 1; b = 0; sel = 1; #5; 
    a = 1; b = 1; sel = 0; #5; 
    a = 1; b = 1; sel = 1; #5; 
    
  end
endmodule

gates/mux/dump.vcd
$date
	Sun Jun 26 21:33:39 2022
$end
$version
	Icarus Verilog
$end
$timescale
	1s
$end
$scope module mux_tb $end
$var wire 1 ! out $end
$var reg 1 " a $end
$var reg 1 # b $end
$var reg 1 $ sel $end
$scope module UUT $end
$var wire 1 " a $end
$var wire 1 # b $end
$var wire 1 $ sel $end
$var reg 1 ! out $end
$upscope $end
$upscope $end
$enddefinitions $end
#0
$dumpvars
0$
0#
0"
0!
$end
#5
1$
#10
1!
0$
1#
#15
0!
1$
#20
0$
0#
1"
#25
1!
1$
#30
0$
1#
#35
1$
